Metadata-Version: 2.1
Name: modified-repository-scorer
Version: 0.5.1
Summary: A python package to compute a repository best engineering practices indicators
Home-page: https://github.com/GerardoBrescia/radon-repository-scorer
Author: Gerardo Brescia
Author-email: gerrybrescia99@gmail.com
Classifier: Development Status :: 5 - Production/Stable
Classifier: Environment :: Console
Classifier: Intended Audience :: Developers
Classifier: Intended Audience :: Science/Research
Classifier: License :: OSI Approved :: Apache Software License
Classifier: Programming Language :: Python :: 3.6
Classifier: Programming Language :: Python :: 3.7
Classifier: Programming Language :: Python :: 3.8
Classifier: Programming Language :: Python :: 3.9
Classifier: Topic :: Software Development :: Libraries :: Python Modules
Classifier: Operating System :: OS Independent
Requires-Python: >=3.6
Requires-Dist: python-dotenv (~=0.14.0)
Requires-Dist: PyDriller (~=2.0)
Requires-Dist: PyGithub (~=1.53)
Requires-Dist: pygount (~=1.2.4)
Requires-Dist: python-gitlab (~=2.5.0)
